camera_intrinsics/__init__.py
camera_intrinsics/base.py
camera_intrinsics/test_base.py
camera_intrinsics-0.0.2.dist-info/LICENSE
camera_intrinsics-0.0.2.dist-info/METADATA
camera_intrinsics-0.0.2.dist-info/WHEEL
camera_intrinsics-0.0.2.dist-info/top_level.txt
camera_intrinsics-0.0.2.dist-info/RECORD
