Metadata-Version: 2.1
Name: camera-intrinsics
Version: 0.0.2
Summary: A package for applying image transformations to the camera intrinsics.
Home-page: https://lukaskoestler.com
Author: Lukas Koestler
Author-email: lkskstlr@gmail.com
License: UNKNOWN
Platform: UNKNOWN
Classifier: Programming Language :: Python :: 3
Classifier: License :: OSI Approved :: MIT License
Classifier: Operating System :: OS Independent
Requires-Python: >=3.5
